BlueDesc/ODDescriptors.jar
BlueDesc/__init__.py
BlueDesc-2008.10.3.dist-info/LICENSE
BlueDesc-2008.10.3.dist-info/METADATA
BlueDesc-2008.10.3.dist-info/WHEEL
BlueDesc-2008.10.3.dist-info/top_level.txt
BlueDesc-2008.10.3.dist-info/RECORD
