Metadata-Version: 2.1
Name: BlueDesc
Version: 2008.10.3
Summary: BlueDesc - Molecular Descriptor Calculator
Home-page: https://github.com/OlivierBeq/BlueDesc
Author: Georg Hinselmann
Author-email: "georg.hinselmann@uni-tuebingen.de"
Maintainer: Olivier J. M. Béquignon
Maintainer-email: "olivier.bequignon.maintainer@gmail.com"
Keywords: BlueDesc,molecular fingerprints,cheminformatics,toxicoinformatics,QSAR
Classifier: Development Status :: 5 - Production/Stable
Classifier: License :: OSI Approved :: GNU General Public License v3 (GPLv3)
Classifier: Programming Language :: Python :: 3.10
Classifier: Programming Language :: Python :: 3.9
Classifier: Programming Language :: Python :: 3.8
Classifier: Programming Language :: Python :: 3.7
Classifier: Programming Language :: Python :: 3.6
License-File: LICENSE
